sitecheck/__init__.py
sitecheck/__main__.py
sitecheck/projects.ini
sitecheck/Scanner/__init__.py
sitecheck/Scanner/__pycache__/__init__.cpython-38.pyc
sitecheck/Scanner/collection_tools/Data_check.py
sitecheck/Scanner/collection_tools/__init__.py
sitecheck/Scanner/collection_tools/amts.py
sitecheck/Scanner/collection_tools/loggernet.py
sitecheck/Scanner/collection_tools/senseive.py
sitecheck/Scanner/collection_tools/utlis.py
sitecheck/Scanner/scanner/__init__.py
sitecheck/Scanner/scanner/config.py
sitecheck/Scanner/scanner/data.py
sitecheck/Scanner/scanner/endpoints.py
sitecheck/Scanner/scanner/options.py
sitecheck/Scanner/scanner/projecthandler.py
sitecheck/Scanner/scanner/utlis.py
sitecheck/Scanner/scanner/__pycache__/__init__.cpython-38.pyc
sitecheck/Scanner/scanner/__pycache__/config.cpython-38.pyc
sitecheck/Scanner/scanner/__pycache__/data.cpython-38.pyc
sitecheck/Scanner/scanner/__pycache__/endpoints.cpython-38.pyc
sitecheck/Scanner/scanner/__pycache__/options.cpython-38.pyc
sitecheck/Scanner/scanner/__pycache__/projecthandler.cpython-38.pyc
sitecheck/Scanner/scanner/__pycache__/utlis.cpython-38.pyc
sitecheck/Scanner/scanner/adaptivecards/__init__.py
sitecheck/Scanner/scanner/adaptivecards/generator.py
sitecheck/Scanner/scanner/adaptivecards/template.py
sitecheck/Scanner/scanner/adaptivecards/__pycache__/__init__.cpython-38.pyc
sitecheck/Scanner/scanner/adaptivecards/__pycache__/generator.cpython-38.pyc
sitecheck/Scanner/scanner/adaptivecards/__pycache__/template.cpython-38.pyc
sitecheck/Scanner/scanner/pyppet/__init__.py
sitecheck/Scanner/scanner/pyppet/amp.py
sitecheck/Scanner/scanner/pyppet/quickview.py
sitecheck/Scanner/scanner/pyppet/sites.py
sitecheck/Scanner/scanner/pyppet/text.py
sitecheck/Scanner/scanner/pyppet/utlis.py
sitecheck/Scanner/scanner/pyppet/__pycache__/__init__.cpython-38.pyc
sitecheck/Scanner/scanner/pyppet/__pycache__/amp.cpython-38.pyc
sitecheck-0.8.4.1.dist-info/DESCRIPTION.rst
sitecheck-0.8.4.1.dist-info/METADATA
sitecheck-0.8.4.1.dist-info/RECORD
sitecheck-0.8.4.1.dist-info/WHEEL
sitecheck-0.8.4.1.dist-info/metadata.json
sitecheck-0.8.4.1.dist-info/top_level.txt
