Metadata-Version: 2.0
Name: sitecheck
Version: 0.8.4.1
Summary: Sitecheck toolkit for Geo-Instruments
Home-page: https://github.com/DanEdens/Sitecheck_Scrapper
Author: Dan.Edens
Author-email: Dan.Edens@geo-instruments.com
License: UNKNOWN
Platform: UNKNOWN
Requires-Python: >=3.7
Requires-Dist: appdirs (>=1.4.4)
Requires-Dist: pyee (>=7.0.2)
Requires-Dist: pyppeteer (>=0.2.2)
Requires-Dist: python-dateutil (>=2.8.1)
Requires-Dist: six (>=1.10.0)
Requires-Dist: texttable (>=1.6.2)
Requires-Dist: urllib3 (>=1.25.9)
Requires-Dist: websockets (>=8.1)
